readExcelFile/__init__.py
readExcelFile/readExcelDataWithXlrd.py
readExcelFile/readExcelWithOpenpyxl.py
readExcelFile/readExcelWithPandas.py
readExcelFile/readFilesWithXlwings.py
readExcelFile-1.0.1.dist-info/METADATA
readExcelFile-1.0.1.dist-info/WHEEL
readExcelFile-1.0.1.dist-info/top_level.txt
readExcelFile-1.0.1.dist-info/RECORD
